{
  "categories": [
    "전 체",
    "예술 콘텐츠",
    "예술 정보",
    "문화공간",
    "전시/미술관",
    "구매 및 소장"
  ],
  "magazines": [
    {
      "title": "'Across the Universe' 어지인 작가",
      "creator": {
        "name": "어지인",
        "iconSrc": "https://7pictures.co.kr/wp-content/plugins/korea-sns/icons/facebook.png"
      },
      "imgSrc": "/assets/images/magazine-thumbnail.jpg",
      "category": "예술 콘텐츠",
      "descriptions": [
        "관객과 작품으로 소통하기 위해서",
        "누구나 알고 있는 자연을 작품의 소재로 선택하고,",
        "나만의 색과 기법을 통해 작품에 감성을 담아낸다."
      ],
      "contents": [
        {
          "type": "text",
          "content": "관객과 작품으로 소통하기 위해서 누구나 알고 있는 자연을 작품의 소재로 선택하고, 나만의 색과 기법을 통해 작품에 감성을 담아낸다. 관객 또한 자연을 그린 작품을 보며 자신만의 감성으로 그 대상을 받아드린다.\n\n결국 작품은 하나이지만 그 작품이 다양한 의미로 다시 태어나는 것, 그래서 작가와 관객 모두 작품을 통해 자신만의 감성을 경험하고 공유하는 것, 그것이 바로 내가 생각하는 작품을 통한 ‘소통’이다.\n\n이전 전시 : ‘색, 괜찮아 잘하고 있어’_어지인, 김태경"
        }
      ],
      "artworks": [
        {
          "imgSrc": "https://i0.wp.com/7pictures.co.kr/wp-content/uploads/2016/10/%ED%81%AC%EA%B8%B0%EB%B3%80%ED%99%98_KakaoTalk_20161012_114414382.jpg?zoom=2&fit=710%2C710&ssl=1",
          "description": "Blossom light, the moon, acrylic on canvas 30cm_2016 / 300,000원"
        },
        {
          "imgSrc": "https://i0.wp.com/7pictures.co.kr/wp-content/uploads/2016/10/%ED%81%AC%EA%B8%B0%EB%B3%80%ED%99%98_KakaoTalk_20161012_114414382.jpg?zoom=2&fit=710%2C710&ssl=1",
          "description": "Blossom light, the moon, acrylic on canvas 30cm_2016 / 300,000원"
        },
        {
          "imgSrc": "https://i0.wp.com/7pictures.co.kr/wp-content/uploads/2016/10/%ED%81%AC%EA%B8%B0%EB%B3%80%ED%99%98_KakaoTalk_20161012_114414382.jpg?zoom=2&fit=710%2C710&ssl=1",
          "description": "Blossom light, the moon, acrylic on canvas 30cm_2016 / 300,000원"
        },
        {
          "imgSrc": "https://i0.wp.com/7pictures.co.kr/wp-content/uploads/2016/10/%ED%81%AC%EA%B8%B0%EB%B3%80%ED%99%98_KakaoTalk_20161012_114414382.jpg?zoom=2&fit=710%2C710&ssl=1",
          "description": "Blossom light, the moon, acrylic on canvas 30cm_2016 / 300,000원"
        }
      ]
    },
    {
      "title": "'Across the Universe' 어지인 작가",
      "creator": {
        "name": "어지인",
        "iconSrc": "https://7pictures.co.kr/wp-content/plugins/korea-sns/icons/facebook.png"
      },
      "imgSrc": "/assets/images/magazine-thumbnail.jpg",
      "category": "예술 콘텐츠",
      "descriptions": [
        "관객과 작품으로 소통하기 위해서",
        "누구나 알고 있는 자연을 작품의 소재로 선택하고,",
        "나만의 색과 기법을 통해 작품에 감성을 담아낸다."
      ],
      "contents": [
        {
          "type": "text",
          "content": "관객과 작품으로 소통하기 위해서 누구나 알고 있는 자연을 작품의 소재로 선택하고, 나만의 색과 기법을 통해 작품에 감성을 담아낸다. 관객 또한 자연을 그린 작품을 보며 자신만의 감성으로 그 대상을 받아드린다.\n\n결국 작품은 하나이지만 그 작품이 다양한 의미로 다시 태어나는 것, 그래서 작가와 관객 모두 작품을 통해 자신만의 감성을 경험하고 공유하는 것, 그것이 바로 내가 생각하는 작품을 통한 ‘소통’이다.\n\n이전 전시 : ‘색, 괜찮아 잘하고 있어’_어지인, 김태경"
        }
      ],
      "artworks": [
        {
          "imgSrc": "https://i0.wp.com/7pictures.co.kr/wp-content/uploads/2016/10/%ED%81%AC%EA%B8%B0%EB%B3%80%ED%99%98_KakaoTalk_20161012_114414382.jpg?zoom=2&fit=710%2C710&ssl=1",
          "description": "Blossom light, the moon, acrylic on canvas 30cm_2016 / 300,000원"
        },
        {
          "imgSrc": "https://i0.wp.com/7pictures.co.kr/wp-content/uploads/2016/10/%ED%81%AC%EA%B8%B0%EB%B3%80%ED%99%98_KakaoTalk_20161012_114414382.jpg?zoom=2&fit=710%2C710&ssl=1",
          "description": "Blossom light, the moon, acrylic on canvas 30cm_2016 / 300,000원"
        },
        {
          "imgSrc": "https://i0.wp.com/7pictures.co.kr/wp-content/uploads/2016/10/%ED%81%AC%EA%B8%B0%EB%B3%80%ED%99%98_KakaoTalk_20161012_114414382.jpg?zoom=2&fit=710%2C710&ssl=1",
          "description": "Blossom light, the moon, acrylic on canvas 30cm_2016 / 300,000원"
        },
        {
          "imgSrc": "https://i0.wp.com/7pictures.co.kr/wp-content/uploads/2016/10/%ED%81%AC%EA%B8%B0%EB%B3%80%ED%99%98_KakaoTalk_20161012_114414382.jpg?zoom=2&fit=710%2C710&ssl=1",
          "description": "Blossom light, the moon, acrylic on canvas 30cm_2016 / 300,000원"
        }
      ]
    },
    {
      "title": "'Across the Universe' 어지인 작가",
      "creator": {
        "name": "어지인",
        "iconSrc": "https://7pictures.co.kr/wp-content/plugins/korea-sns/icons/facebook.png"
      },
      "imgSrc": "/assets/images/magazine-thumbnail.jpg",
      "category": "예술 콘텐츠",
      "descriptions": [
        "관객과 작품으로 소통하기 위해서",
        "누구나 알고 있는 자연을 작품의 소재로 선택하고,",
        "나만의 색과 기법을 통해 작품에 감성을 담아낸다."
      ],
      "contents": [
        {
          "type": "text",
          "content": "관객과 작품으로 소통하기 위해서 누구나 알고 있는 자연을 작품의 소재로 선택하고, 나만의 색과 기법을 통해 작품에 감성을 담아낸다. 관객 또한 자연을 그린 작품을 보며 자신만의 감성으로 그 대상을 받아드린다.\n\n결국 작품은 하나이지만 그 작품이 다양한 의미로 다시 태어나는 것, 그래서 작가와 관객 모두 작품을 통해 자신만의 감성을 경험하고 공유하는 것, 그것이 바로 내가 생각하는 작품을 통한 ‘소통’이다.\n\n이전 전시 : ‘색, 괜찮아 잘하고 있어’_어지인, 김태경"
        }
      ],
      "artworks": [
        {
          "imgSrc": "https://i0.wp.com/7pictures.co.kr/wp-content/uploads/2016/10/%ED%81%AC%EA%B8%B0%EB%B3%80%ED%99%98_KakaoTalk_20161012_114414382.jpg?zoom=2&fit=710%2C710&ssl=1",
          "description": "Blossom light, the moon, acrylic on canvas 30cm_2016 / 300,000원"
        },
        {
          "imgSrc": "https://i0.wp.com/7pictures.co.kr/wp-content/uploads/2016/10/%ED%81%AC%EA%B8%B0%EB%B3%80%ED%99%98_KakaoTalk_20161012_114414382.jpg?zoom=2&fit=710%2C710&ssl=1",
          "description": "Blossom light, the moon, acrylic on canvas 30cm_2016 / 300,000원"
        },
        {
          "imgSrc": "https://i0.wp.com/7pictures.co.kr/wp-content/uploads/2016/10/%ED%81%AC%EA%B8%B0%EB%B3%80%ED%99%98_KakaoTalk_20161012_114414382.jpg?zoom=2&fit=710%2C710&ssl=1",
          "description": "Blossom light, the moon, acrylic on canvas 30cm_2016 / 300,000원"
        },
        {
          "imgSrc": "https://i0.wp.com/7pictures.co.kr/wp-content/uploads/2016/10/%ED%81%AC%EA%B8%B0%EB%B3%80%ED%99%98_KakaoTalk_20161012_114414382.jpg?zoom=2&fit=710%2C710&ssl=1",
          "description": "Blossom light, the moon, acrylic on canvas 30cm_2016 / 300,000원"
        }
      ]
    },
    {
      "title": "'Across the Universe' 어지인 작가",
      "creator": {
        "name": "어지인",
        "iconSrc": "https://7pictures.co.kr/wp-content/plugins/korea-sns/icons/facebook.png"
      },
      "imgSrc": "/assets/images/magazine-thumbnail.jpg",
      "category": "예술 콘텐츠",
      "descriptions": [
        "관객과 작품으로 소통하기 위해서",
        "누구나 알고 있는 자연을 작품의 소재로 선택하고,",
        "나만의 색과 기법을 통해 작품에 감성을 담아낸다."
      ],
      "contents": [
        {
          "type": "text",
          "content": "관객과 작품으로 소통하기 위해서 누구나 알고 있는 자연을 작품의 소재로 선택하고, 나만의 색과 기법을 통해 작품에 감성을 담아낸다. 관객 또한 자연을 그린 작품을 보며 자신만의 감성으로 그 대상을 받아드린다.\n\n결국 작품은 하나이지만 그 작품이 다양한 의미로 다시 태어나는 것, 그래서 작가와 관객 모두 작품을 통해 자신만의 감성을 경험하고 공유하는 것, 그것이 바로 내가 생각하는 작품을 통한 ‘소통’이다.\n\n이전 전시 : ‘색, 괜찮아 잘하고 있어’_어지인, 김태경"
        }
      ],
      "artworks": [
        {
          "imgSrc": "https://i0.wp.com/7pictures.co.kr/wp-content/uploads/2016/10/%ED%81%AC%EA%B8%B0%EB%B3%80%ED%99%98_KakaoTalk_20161012_114414382.jpg?zoom=2&fit=710%2C710&ssl=1",
          "description": "Blossom light, the moon, acrylic on canvas 30cm_2016 / 300,000원"
        },
        {
          "imgSrc": "https://i0.wp.com/7pictures.co.kr/wp-content/uploads/2016/10/%ED%81%AC%EA%B8%B0%EB%B3%80%ED%99%98_KakaoTalk_20161012_114414382.jpg?zoom=2&fit=710%2C710&ssl=1",
          "description": "Blossom light, the moon, acrylic on canvas 30cm_2016 / 300,000원"
        },
        {
          "imgSrc": "https://i0.wp.com/7pictures.co.kr/wp-content/uploads/2016/10/%ED%81%AC%EA%B8%B0%EB%B3%80%ED%99%98_KakaoTalk_20161012_114414382.jpg?zoom=2&fit=710%2C710&ssl=1",
          "description": "Blossom light, the moon, acrylic on canvas 30cm_2016 / 300,000원"
        },
        {
          "imgSrc": "https://i0.wp.com/7pictures.co.kr/wp-content/uploads/2016/10/%ED%81%AC%EA%B8%B0%EB%B3%80%ED%99%98_KakaoTalk_20161012_114414382.jpg?zoom=2&fit=710%2C710&ssl=1",
          "description": "Blossom light, the moon, acrylic on canvas 30cm_2016 / 300,000원"
        }
      ]
    },
    {
      "title": "'Across the Universe' 어지인 작가",
      "creator": {
        "name": "어지인",
        "iconSrc": "https://7pictures.co.kr/wp-content/plugins/korea-sns/icons/facebook.png"
      },
      "imgSrc": "/assets/images/magazine-thumbnail.jpg",
      "category": "예술 콘텐츠",
      "descriptions": [
        "관객과 작품으로 소통하기 위해서",
        "누구나 알고 있는 자연을 작품의 소재로 선택하고,",
        "나만의 색과 기법을 통해 작품에 감성을 담아낸다."
      ],
      "contents": [
        {
          "type": "text",
          "content": "관객과 작품으로 소통하기 위해서 누구나 알고 있는 자연을 작품의 소재로 선택하고, 나만의 색과 기법을 통해 작품에 감성을 담아낸다. 관객 또한 자연을 그린 작품을 보며 자신만의 감성으로 그 대상을 받아드린다.\n\n결국 작품은 하나이지만 그 작품이 다양한 의미로 다시 태어나는 것, 그래서 작가와 관객 모두 작품을 통해 자신만의 감성을 경험하고 공유하는 것, 그것이 바로 내가 생각하는 작품을 통한 ‘소통’이다.\n\n이전 전시 : ‘색, 괜찮아 잘하고 있어’_어지인, 김태경"
        }
      ],
      "artworks": [
        {
          "imgSrc": "https://i0.wp.com/7pictures.co.kr/wp-content/uploads/2016/10/%ED%81%AC%EA%B8%B0%EB%B3%80%ED%99%98_KakaoTalk_20161012_114414382.jpg?zoom=2&fit=710%2C710&ssl=1",
          "description": "Blossom light, the moon, acrylic on canvas 30cm_2016 / 300,000원"
        },
        {
          "imgSrc": "https://i0.wp.com/7pictures.co.kr/wp-content/uploads/2016/10/%ED%81%AC%EA%B8%B0%EB%B3%80%ED%99%98_KakaoTalk_20161012_114414382.jpg?zoom=2&fit=710%2C710&ssl=1",
          "description": "Blossom light, the moon, acrylic on canvas 30cm_2016 / 300,000원"
        },
        {
          "imgSrc": "https://i0.wp.com/7pictures.co.kr/wp-content/uploads/2016/10/%ED%81%AC%EA%B8%B0%EB%B3%80%ED%99%98_KakaoTalk_20161012_114414382.jpg?zoom=2&fit=710%2C710&ssl=1",
          "description": "Blossom light, the moon, acrylic on canvas 30cm_2016 / 300,000원"
        },
        {
          "imgSrc": "https://i0.wp.com/7pictures.co.kr/wp-content/uploads/2016/10/%ED%81%AC%EA%B8%B0%EB%B3%80%ED%99%98_KakaoTalk_20161012_114414382.jpg?zoom=2&fit=710%2C710&ssl=1",
          "description": "Blossom light, the moon, acrylic on canvas 30cm_2016 / 300,000원"
        }
      ]
    },
    {
      "title": "'Across the Universe' 어지인 작가",
      "creator": {
        "name": "어지인",
        "iconSrc": "https://7pictures.co.kr/wp-content/plugins/korea-sns/icons/facebook.png"
      },
      "imgSrc": "/assets/images/magazine-thumbnail.jpg",
      "category": "예술 콘텐츠",
      "descriptions": [
        "관객과 작품으로 소통하기 위해서",
        "누구나 알고 있는 자연을 작품의 소재로 선택하고,",
        "나만의 색과 기법을 통해 작품에 감성을 담아낸다."
      ],
      "contents": [
        {
          "type": "text",
          "content": "관객과 작품으로 소통하기 위해서 누구나 알고 있는 자연을 작품의 소재로 선택하고, 나만의 색과 기법을 통해 작품에 감성을 담아낸다. 관객 또한 자연을 그린 작품을 보며 자신만의 감성으로 그 대상을 받아드린다.\n\n결국 작품은 하나이지만 그 작품이 다양한 의미로 다시 태어나는 것, 그래서 작가와 관객 모두 작품을 통해 자신만의 감성을 경험하고 공유하는 것, 그것이 바로 내가 생각하는 작품을 통한 ‘소통’이다.\n\n이전 전시 : ‘색, 괜찮아 잘하고 있어’_어지인, 김태경"
        }
      ],
      "artworks": [
        {
          "imgSrc": "https://i0.wp.com/7pictures.co.kr/wp-content/uploads/2016/10/%ED%81%AC%EA%B8%B0%EB%B3%80%ED%99%98_KakaoTalk_20161012_114414382.jpg?zoom=2&fit=710%2C710&ssl=1",
          "description": "Blossom light, the moon, acrylic on canvas 30cm_2016 / 300,000원"
        },
        {
          "imgSrc": "https://i0.wp.com/7pictures.co.kr/wp-content/uploads/2016/10/%ED%81%AC%EA%B8%B0%EB%B3%80%ED%99%98_KakaoTalk_20161012_114414382.jpg?zoom=2&fit=710%2C710&ssl=1",
          "description": "Blossom light, the moon, acrylic on canvas 30cm_2016 / 300,000원"
        },
        {
          "imgSrc": "https://i0.wp.com/7pictures.co.kr/wp-content/uploads/2016/10/%ED%81%AC%EA%B8%B0%EB%B3%80%ED%99%98_KakaoTalk_20161012_114414382.jpg?zoom=2&fit=710%2C710&ssl=1",
          "description": "Blossom light, the moon, acrylic on canvas 30cm_2016 / 300,000원"
        },
        {
          "imgSrc": "https://i0.wp.com/7pictures.co.kr/wp-content/uploads/2016/10/%ED%81%AC%EA%B8%B0%EB%B3%80%ED%99%98_KakaoTalk_20161012_114414382.jpg?zoom=2&fit=710%2C710&ssl=1",
          "description": "Blossom light, the moon, acrylic on canvas 30cm_2016 / 300,000원"
        }
      ]
    },
    {
      "title": "'Across the Universe' 어지인 작가",
      "creator": {
        "name": "어지인",
        "iconSrc": "https://7pictures.co.kr/wp-content/plugins/korea-sns/icons/facebook.png"
      },
      "imgSrc": "/assets/images/magazine-thumbnail.jpg",
      "category": "예술 콘텐츠",
      "descriptions": [
        "관객과 작품으로 소통하기 위해서",
        "누구나 알고 있는 자연을 작품의 소재로 선택하고,",
        "나만의 색과 기법을 통해 작품에 감성을 담아낸다."
      ],
      "contents": [
        {
          "type": "text",
          "content": "관객과 작품으로 소통하기 위해서 누구나 알고 있는 자연을 작품의 소재로 선택하고, 나만의 색과 기법을 통해 작품에 감성을 담아낸다. 관객 또한 자연을 그린 작품을 보며 자신만의 감성으로 그 대상을 받아드린다.\n\n결국 작품은 하나이지만 그 작품이 다양한 의미로 다시 태어나는 것, 그래서 작가와 관객 모두 작품을 통해 자신만의 감성을 경험하고 공유하는 것, 그것이 바로 내가 생각하는 작품을 통한 ‘소통’이다.\n\n이전 전시 : ‘색, 괜찮아 잘하고 있어’_어지인, 김태경"
        }
      ],
      "artworks": [
        {
          "imgSrc": "https://i0.wp.com/7pictures.co.kr/wp-content/uploads/2016/10/%ED%81%AC%EA%B8%B0%EB%B3%80%ED%99%98_KakaoTalk_20161012_114414382.jpg?zoom=2&fit=710%2C710&ssl=1",
          "description": "Blossom light, the moon, acrylic on canvas 30cm_2016 / 300,000원"
        },
        {
          "imgSrc": "https://i0.wp.com/7pictures.co.kr/wp-content/uploads/2016/10/%ED%81%AC%EA%B8%B0%EB%B3%80%ED%99%98_KakaoTalk_20161012_114414382.jpg?zoom=2&fit=710%2C710&ssl=1",
          "description": "Blossom light, the moon, acrylic on canvas 30cm_2016 / 300,000원"
        },
        {
          "imgSrc": "https://i0.wp.com/7pictures.co.kr/wp-content/uploads/2016/10/%ED%81%AC%EA%B8%B0%EB%B3%80%ED%99%98_KakaoTalk_20161012_114414382.jpg?zoom=2&fit=710%2C710&ssl=1",
          "description": "Blossom light, the moon, acrylic on canvas 30cm_2016 / 300,000원"
        },
        {
          "imgSrc": "https://i0.wp.com/7pictures.co.kr/wp-content/uploads/2016/10/%ED%81%AC%EA%B8%B0%EB%B3%80%ED%99%98_KakaoTalk_20161012_114414382.jpg?zoom=2&fit=710%2C710&ssl=1",
          "description": "Blossom light, the moon, acrylic on canvas 30cm_2016 / 300,000원"
        }
      ]
    },
    {
      "title": "'Across the Universe' 어지인 작가",
      "creator": {
        "name": "어지인",
        "iconSrc": "https://7pictures.co.kr/wp-content/plugins/korea-sns/icons/facebook.png"
      },
      "imgSrc": "/assets/images/magazine-thumbnail.jpg",
      "category": "예술 콘텐츠",
      "descriptions": [
        "관객과 작품으로 소통하기 위해서",
        "누구나 알고 있는 자연을 작품의 소재로 선택하고,",
        "나만의 색과 기법을 통해 작품에 감성을 담아낸다."
      ],
      "contents": [
        {
          "type": "text",
          "content": "관객과 작품으로 소통하기 위해서 누구나 알고 있는 자연을 작품의 소재로 선택하고, 나만의 색과 기법을 통해 작품에 감성을 담아낸다. 관객 또한 자연을 그린 작품을 보며 자신만의 감성으로 그 대상을 받아드린다.\n\n결국 작품은 하나이지만 그 작품이 다양한 의미로 다시 태어나는 것, 그래서 작가와 관객 모두 작품을 통해 자신만의 감성을 경험하고 공유하는 것, 그것이 바로 내가 생각하는 작품을 통한 ‘소통’이다.\n\n이전 전시 : ‘색, 괜찮아 잘하고 있어’_어지인, 김태경"
        }
      ],
      "artworks": [
        {
          "imgSrc": "https://i0.wp.com/7pictures.co.kr/wp-content/uploads/2016/10/%ED%81%AC%EA%B8%B0%EB%B3%80%ED%99%98_KakaoTalk_20161012_114414382.jpg?zoom=2&fit=710%2C710&ssl=1",
          "description": "Blossom light, the moon, acrylic on canvas 30cm_2016 / 300,000원"
        },
        {
          "imgSrc": "https://i0.wp.com/7pictures.co.kr/wp-content/uploads/2016/10/%ED%81%AC%EA%B8%B0%EB%B3%80%ED%99%98_KakaoTalk_20161012_114414382.jpg?zoom=2&fit=710%2C710&ssl=1",
          "description": "Blossom light, the moon, acrylic on canvas 30cm_2016 / 300,000원"
        },
        {
          "imgSrc": "https://i0.wp.com/7pictures.co.kr/wp-content/uploads/2016/10/%ED%81%AC%EA%B8%B0%EB%B3%80%ED%99%98_KakaoTalk_20161012_114414382.jpg?zoom=2&fit=710%2C710&ssl=1",
          "description": "Blossom light, the moon, acrylic on canvas 30cm_2016 / 300,000원"
        },
        {
          "imgSrc": "https://i0.wp.com/7pictures.co.kr/wp-content/uploads/2016/10/%ED%81%AC%EA%B8%B0%EB%B3%80%ED%99%98_KakaoTalk_20161012_114414382.jpg?zoom=2&fit=710%2C710&ssl=1",
          "description": "Blossom light, the moon, acrylic on canvas 30cm_2016 / 300,000원"
        }
      ]
    },
    {
      "title": "'Across the Universe' 어지인 작가",
      "creator": {
        "name": "어지인",
        "iconSrc": "https://7pictures.co.kr/wp-content/plugins/korea-sns/icons/facebook.png"
      },
      "imgSrc": "/assets/images/magazine-thumbnail.jpg",
      "category": "문화공간",
      "descriptions": [
        "관객과 작품으로 소통하기 위해서",
        "누구나 알고 있는 자연을 작품의 소재로 선택하고,",
        "나만의 색과 기법을 통해 작품에 감성을 담아낸다."
      ],
      "contents": [
        {
          "type": "text",
          "content": "관객과 작품으로 소통하기 위해서 누구나 알고 있는 자연을 작품의 소재로 선택하고, 나만의 색과 기법을 통해 작품에 감성을 담아낸다. 관객 또한 자연을 그린 작품을 보며 자신만의 감성으로 그 대상을 받아드린다.\n\n결국 작품은 하나이지만 그 작품이 다양한 의미로 다시 태어나는 것, 그래서 작가와 관객 모두 작품을 통해 자신만의 감성을 경험하고 공유하는 것, 그것이 바로 내가 생각하는 작품을 통한 ‘소통’이다.\n\n이전 전시 : ‘색, 괜찮아 잘하고 있어’_어지인, 김태경"
        }
      ],
      "artworks": [
        {
          "imgSrc": "https://i0.wp.com/7pictures.co.kr/wp-content/uploads/2016/10/%ED%81%AC%EA%B8%B0%EB%B3%80%ED%99%98_KakaoTalk_20161012_114414382.jpg?zoom=2&fit=710%2C710&ssl=1",
          "description": "Blossom light, the moon, acrylic on canvas 30cm_2016 / 300,000원"
        },
        {
          "imgSrc": "https://i0.wp.com/7pictures.co.kr/wp-content/uploads/2016/10/%ED%81%AC%EA%B8%B0%EB%B3%80%ED%99%98_KakaoTalk_20161012_114414382.jpg?zoom=2&fit=710%2C710&ssl=1",
          "description": "Blossom light, the moon, acrylic on canvas 30cm_2016 / 300,000원"
        },
        {
          "imgSrc": "https://i0.wp.com/7pictures.co.kr/wp-content/uploads/2016/10/%ED%81%AC%EA%B8%B0%EB%B3%80%ED%99%98_KakaoTalk_20161012_114414382.jpg?zoom=2&fit=710%2C710&ssl=1",
          "description": "Blossom light, the moon, acrylic on canvas 30cm_2016 / 300,000원"
        },
        {
          "imgSrc": "https://i0.wp.com/7pictures.co.kr/wp-content/uploads/2016/10/%ED%81%AC%EA%B8%B0%EB%B3%80%ED%99%98_KakaoTalk_20161012_114414382.jpg?zoom=2&fit=710%2C710&ssl=1",
          "description": "Blossom light, the moon, acrylic on canvas 30cm_2016 / 300,000원"
        }
      ]
    },
    {
      "title": "'Across the Universe' 어지인 작가",
      "creator": {
        "name": "어지인",
        "iconSrc": "https://7pictures.co.kr/wp-content/plugins/korea-sns/icons/facebook.png"
      },
      "imgSrc": "/assets/images/magazine-thumbnail.jpg",
      "category": "문화공간",
      "descriptions": [
        "관객과 작품으로 소통하기 위해서",
        "누구나 알고 있는 자연을 작품의 소재로 선택하고,",
        "나만의 색과 기법을 통해 작품에 감성을 담아낸다."
      ],
      "contents": [
        {
          "type": "text",
          "content": "관객과 작품으로 소통하기 위해서 누구나 알고 있는 자연을 작품의 소재로 선택하고, 나만의 색과 기법을 통해 작품에 감성을 담아낸다. 관객 또한 자연을 그린 작품을 보며 자신만의 감성으로 그 대상을 받아드린다.\n\n\t결국 작품은 하나이지만 그 작품이 다양한 의미로 다시 태어나는 것, 그래서 작가와 관객 모두 작품을 통해 자신만의 감성을 경험하고 공유하는 것, 그것이 바로 내가 생각하는 작품을 통한 ‘소통’이다.\n\n\t이전 전시 : ‘색, 괜찮아 잘하고 있어’_어지인, 김태경"
        }
      ],
      "artworks": [
        {
          "imgSrc": "https://i0.wp.com/7pictures.co.kr/wp-content/uploads/2016/10/%ED%81%AC%EA%B8%B0%EB%B3%80%ED%99%98_KakaoTalk_20161012_114414382.jpg?zoom=2&fit=710%2C710&ssl=1",
          "description": "Blossom light, the moon, acrylic on canvas 30cm_2016 / 300,000원"
        },
        {
          "imgSrc": "https://i0.wp.com/7pictures.co.kr/wp-content/uploads/2016/10/%ED%81%AC%EA%B8%B0%EB%B3%80%ED%99%98_KakaoTalk_20161012_114414382.jpg?zoom=2&fit=710%2C710&ssl=1",
          "description": "Blossom light, the moon, acrylic on canvas 30cm_2016 / 300,000원"
        },
        {
          "imgSrc": "https://i0.wp.com/7pictures.co.kr/wp-content/uploads/2016/10/%ED%81%AC%EA%B8%B0%EB%B3%80%ED%99%98_KakaoTalk_20161012_114414382.jpg?zoom=2&fit=710%2C710&ssl=1",
          "description": "Blossom light, the moon, acrylic on canvas 30cm_2016 / 300,000원"
        },
        {
          "imgSrc": "https://i0.wp.com/7pictures.co.kr/wp-content/uploads/2016/10/%ED%81%AC%EA%B8%B0%EB%B3%80%ED%99%98_KakaoTalk_20161012_114414382.jpg?zoom=2&fit=710%2C710&ssl=1",
          "description": "Blossom light, the moon, acrylic on canvas 30cm_2016 / 300,000원"
        }
      ]
    },
    {
      "title": "'Across the Universe' 어지인 작가",
      "creator": {
        "name": "어지인",
        "iconSrc": "https://7pictures.co.kr/wp-content/plugins/korea-sns/icons/facebook.png"
      },
      "imgSrc": "/assets/images/magazine-thumbnail.jpg",
      "category": "문화공간",
      "descriptions": [
        "관객과 작품으로 소통하기 위해서",
        "누구나 알고 있는 자연을 작품의 소재로 선택하고,",
        "나만의 색과 기법을 통해 작품에 감성을 담아낸다."
      ],
      "contents": [
        {
          "type": "text",
          "content": "관객과 작품으로 소통하기 위해서 누구나 알고 있는 자연을 작품의 소재로 선택하고, 나만의 색과 기법을 통해 작품에 감성을 담아낸다. 관객 또한 자연을 그린 작품을 보며 자신만의 감성으로 그 대상을 받아드린다.\n\n\t결국 작품은 하나이지만 그 작품이 다양한 의미로 다시 태어나는 것, 그래서 작가와 관객 모두 작품을 통해 자신만의 감성을 경험하고 공유하는 것, 그것이 바로 내가 생각하는 작품을 통한 ‘소통’이다.\n\n\t이전 전시 : ‘색, 괜찮아 잘하고 있어’_어지인, 김태경"
        }
      ],
      "artworks": [
        {
          "imgSrc": "https://i0.wp.com/7pictures.co.kr/wp-content/uploads/2016/10/%ED%81%AC%EA%B8%B0%EB%B3%80%ED%99%98_KakaoTalk_20161012_114414382.jpg?zoom=2&fit=710%2C710&ssl=1",
          "description": "Blossom light, the moon, acrylic on canvas 30cm_2016 / 300,000원"
        },
        {
          "imgSrc": "https://i0.wp.com/7pictures.co.kr/wp-content/uploads/2016/10/%ED%81%AC%EA%B8%B0%EB%B3%80%ED%99%98_KakaoTalk_20161012_114414382.jpg?zoom=2&fit=710%2C710&ssl=1",
          "description": "Blossom light, the moon, acrylic on canvas 30cm_2016 / 300,000원"
        },
        {
          "imgSrc": "https://i0.wp.com/7pictures.co.kr/wp-content/uploads/2016/10/%ED%81%AC%EA%B8%B0%EB%B3%80%ED%99%98_KakaoTalk_20161012_114414382.jpg?zoom=2&fit=710%2C710&ssl=1",
          "description": "Blossom light, the moon, acrylic on canvas 30cm_2016 / 300,000원"
        },
        {
          "imgSrc": "https://i0.wp.com/7pictures.co.kr/wp-content/uploads/2016/10/%ED%81%AC%EA%B8%B0%EB%B3%80%ED%99%98_KakaoTalk_20161012_114414382.jpg?zoom=2&fit=710%2C710&ssl=1",
          "description": "Blossom light, the moon, acrylic on canvas 30cm_2016 / 300,000원"
        }
      ]
    },
    {
      "title": "'Across the Universe' 어지인 작가",
      "creator": {
        "name": "어지인",
        "iconSrc": "https://7pictures.co.kr/wp-content/plugins/korea-sns/icons/facebook.png"
      },
      "imgSrc": "/assets/images/magazine-thumbnail.jpg",
      "category": "문화공간",
      "descriptions": [
        "관객과 작품으로 소통하기 위해서",
        "누구나 알고 있는 자연을 작품의 소재로 선택하고,",
        "나만의 색과 기법을 통해 작품에 감성을 담아낸다."
      ],
      "contents": [
        {
          "type": "text",
          "content": "관객과 작품으로 소통하기 위해서 누구나 알고 있는 자연을 작품의 소재로 선택하고, 나만의 색과 기법을 통해 작품에 감성을 담아낸다. 관객 또한 자연을 그린 작품을 보며 자신만의 감성으로 그 대상을 받아드린다.\n\n\t결국 작품은 하나이지만 그 작품이 다양한 의미로 다시 태어나는 것, 그래서 작가와 관객 모두 작품을 통해 자신만의 감성을 경험하고 공유하는 것, 그것이 바로 내가 생각하는 작품을 통한 ‘소통’이다.\n\n\t이전 전시 : ‘색, 괜찮아 잘하고 있어’_어지인, 김태경"
        }
      ],
      "artworks": [
        {
          "imgSrc": "https://i0.wp.com/7pictures.co.kr/wp-content/uploads/2016/10/%ED%81%AC%EA%B8%B0%EB%B3%80%ED%99%98_KakaoTalk_20161012_114414382.jpg?zoom=2&fit=710%2C710&ssl=1",
          "description": "Blossom light, the moon, acrylic on canvas 30cm_2016 / 300,000원"
        },
        {
          "imgSrc": "https://i0.wp.com/7pictures.co.kr/wp-content/uploads/2016/10/%ED%81%AC%EA%B8%B0%EB%B3%80%ED%99%98_KakaoTalk_20161012_114414382.jpg?zoom=2&fit=710%2C710&ssl=1",
          "description": "Blossom light, the moon, acrylic on canvas 30cm_2016 / 300,000원"
        },
        {
          "imgSrc": "https://i0.wp.com/7pictures.co.kr/wp-content/uploads/2016/10/%ED%81%AC%EA%B8%B0%EB%B3%80%ED%99%98_KakaoTalk_20161012_114414382.jpg?zoom=2&fit=710%2C710&ssl=1",
          "description": "Blossom light, the moon, acrylic on canvas 30cm_2016 / 300,000원"
        },
        {
          "imgSrc": "https://i0.wp.com/7pictures.co.kr/wp-content/uploads/2016/10/%ED%81%AC%EA%B8%B0%EB%B3%80%ED%99%98_KakaoTalk_20161012_114414382.jpg?zoom=2&fit=710%2C710&ssl=1",
          "description": "Blossom light, the moon, acrylic on canvas 30cm_2016 / 300,000원"
        }
      ]
    },
    {
      "title": "'Across the Universe' 어지인 작가",
      "creator": {
        "name": "어지인",
        "iconSrc": "https://7pictures.co.kr/wp-content/plugins/korea-sns/icons/facebook.png"
      },
      "imgSrc": "/assets/images/magazine-thumbnail.jpg",
      "category": "문화공간",
      "descriptions": [
        "관객과 작품으로 소통하기 위해서",
        "누구나 알고 있는 자연을 작품의 소재로 선택하고,",
        "나만의 색과 기법을 통해 작품에 감성을 담아낸다."
      ],
      "contents": [
        {
          "type": "text",
          "content": "관객과 작품으로 소통하기 위해서 누구나 알고 있는 자연을 작품의 소재로 선택하고, 나만의 색과 기법을 통해 작품에 감성을 담아낸다. 관객 또한 자연을 그린 작품을 보며 자신만의 감성으로 그 대상을 받아드린다.\n\n\t결국 작품은 하나이지만 그 작품이 다양한 의미로 다시 태어나는 것, 그래서 작가와 관객 모두 작품을 통해 자신만의 감성을 경험하고 공유하는 것, 그것이 바로 내가 생각하는 작품을 통한 ‘소통’이다.\n\n\t이전 전시 : ‘색, 괜찮아 잘하고 있어’_어지인, 김태경"
        }
      ],
      "artworks": [
        {
          "imgSrc": "https://i0.wp.com/7pictures.co.kr/wp-content/uploads/2016/10/%ED%81%AC%EA%B8%B0%EB%B3%80%ED%99%98_KakaoTalk_20161012_114414382.jpg?zoom=2&fit=710%2C710&ssl=1",
          "description": "Blossom light, the moon, acrylic on canvas 30cm_2016 / 300,000원"
        },
        {
          "imgSrc": "https://i0.wp.com/7pictures.co.kr/wp-content/uploads/2016/10/%ED%81%AC%EA%B8%B0%EB%B3%80%ED%99%98_KakaoTalk_20161012_114414382.jpg?zoom=2&fit=710%2C710&ssl=1",
          "description": "Blossom light, the moon, acrylic on canvas 30cm_2016 / 300,000원"
        },
        {
          "imgSrc": "https://i0.wp.com/7pictures.co.kr/wp-content/uploads/2016/10/%ED%81%AC%EA%B8%B0%EB%B3%80%ED%99%98_KakaoTalk_20161012_114414382.jpg?zoom=2&fit=710%2C710&ssl=1",
          "description": "Blossom light, the moon, acrylic on canvas 30cm_2016 / 300,000원"
        },
        {
          "imgSrc": "https://i0.wp.com/7pictures.co.kr/wp-content/uploads/2016/10/%ED%81%AC%EA%B8%B0%EB%B3%80%ED%99%98_KakaoTalk_20161012_114414382.jpg?zoom=2&fit=710%2C710&ssl=1",
          "description": "Blossom light, the moon, acrylic on canvas 30cm_2016 / 300,000원"
        }
      ]
    },
    {
      "title": "'Across the Universe' 어지인 작가",
      "creator": {
        "name": "어지인",
        "iconSrc": "https://7pictures.co.kr/wp-content/plugins/korea-sns/icons/facebook.png"
      },
      "imgSrc": "/assets/images/magazine-thumbnail.jpg",
      "category": "문화공간",
      "descriptions": [
        "관객과 작품으로 소통하기 위해서",
        "누구나 알고 있는 자연을 작품의 소재로 선택하고,",
        "나만의 색과 기법을 통해 작품에 감성을 담아낸다."
      ],
      "contents": [
        {
          "type": "text",
          "content": "관객과 작품으로 소통하기 위해서 누구나 알고 있는 자연을 작품의 소재로 선택하고, 나만의 색과 기법을 통해 작품에 감성을 담아낸다. 관객 또한 자연을 그린 작품을 보며 자신만의 감성으로 그 대상을 받아드린다.\n\n\t결국 작품은 하나이지만 그 작품이 다양한 의미로 다시 태어나는 것, 그래서 작가와 관객 모두 작품을 통해 자신만의 감성을 경험하고 공유하는 것, 그것이 바로 내가 생각하는 작품을 통한 ‘소통’이다.\n\n\t이전 전시 : ‘색, 괜찮아 잘하고 있어’_어지인, 김태경"
        }
      ],
      "artworks": [
        {
          "imgSrc": "https://i0.wp.com/7pictures.co.kr/wp-content/uploads/2016/10/%ED%81%AC%EA%B8%B0%EB%B3%80%ED%99%98_KakaoTalk_20161012_114414382.jpg?zoom=2&fit=710%2C710&ssl=1",
          "description": "Blossom light, the moon, acrylic on canvas 30cm_2016 / 300,000원"
        },
        {
          "imgSrc": "https://i0.wp.com/7pictures.co.kr/wp-content/uploads/2016/10/%ED%81%AC%EA%B8%B0%EB%B3%80%ED%99%98_KakaoTalk_20161012_114414382.jpg?zoom=2&fit=710%2C710&ssl=1",
          "description": "Blossom light, the moon, acrylic on canvas 30cm_2016 / 300,000원"
        },
        {
          "imgSrc": "https://i0.wp.com/7pictures.co.kr/wp-content/uploads/2016/10/%ED%81%AC%EA%B8%B0%EB%B3%80%ED%99%98_KakaoTalk_20161012_114414382.jpg?zoom=2&fit=710%2C710&ssl=1",
          "description": "Blossom light, the moon, acrylic on canvas 30cm_2016 / 300,000원"
        },
        {
          "imgSrc": "https://i0.wp.com/7pictures.co.kr/wp-content/uploads/2016/10/%ED%81%AC%EA%B8%B0%EB%B3%80%ED%99%98_KakaoTalk_20161012_114414382.jpg?zoom=2&fit=710%2C710&ssl=1",
          "description": "Blossom light, the moon, acrylic on canvas 30cm_2016 / 300,000원"
        }
      ]
    },
    {
      "title": "'Across the Universe' 어지인 작가",
      "creator": {
        "name": "어지인",
        "iconSrc": "https://7pictures.co.kr/wp-content/plugins/korea-sns/icons/facebook.png"
      },
      "imgSrc": "/assets/images/magazine-thumbnail.jpg",
      "category": "문화공간",
      "descriptions": [
        "관객과 작품으로 소통하기 위해서",
        "누구나 알고 있는 자연을 작품의 소재로 선택하고,",
        "나만의 색과 기법을 통해 작품에 감성을 담아낸다."
      ],
      "contents": [
        {
          "type": "text",
          "content": "관객과 작품으로 소통하기 위해서 누구나 알고 있는 자연을 작품의 소재로 선택하고, 나만의 색과 기법을 통해 작품에 감성을 담아낸다. 관객 또한 자연을 그린 작품을 보며 자신만의 감성으로 그 대상을 받아드린다.\n\n\t결국 작품은 하나이지만 그 작품이 다양한 의미로 다시 태어나는 것, 그래서 작가와 관객 모두 작품을 통해 자신만의 감성을 경험하고 공유하는 것, 그것이 바로 내가 생각하는 작품을 통한 ‘소통’이다.\n\n\t이전 전시 : ‘색, 괜찮아 잘하고 있어’_어지인, 김태경"
        }
      ],
      "artworks": [
        {
          "imgSrc": "https://i0.wp.com/7pictures.co.kr/wp-content/uploads/2016/10/%ED%81%AC%EA%B8%B0%EB%B3%80%ED%99%98_KakaoTalk_20161012_114414382.jpg?zoom=2&fit=710%2C710&ssl=1",
          "description": "Blossom light, the moon, acrylic on canvas 30cm_2016 / 300,000원"
        },
        {
          "imgSrc": "https://i0.wp.com/7pictures.co.kr/wp-content/uploads/2016/10/%ED%81%AC%EA%B8%B0%EB%B3%80%ED%99%98_KakaoTalk_20161012_114414382.jpg?zoom=2&fit=710%2C710&ssl=1",
          "description": "Blossom light, the moon, acrylic on canvas 30cm_2016 / 300,000원"
        },
        {
          "imgSrc": "https://i0.wp.com/7pictures.co.kr/wp-content/uploads/2016/10/%ED%81%AC%EA%B8%B0%EB%B3%80%ED%99%98_KakaoTalk_20161012_114414382.jpg?zoom=2&fit=710%2C710&ssl=1",
          "description": "Blossom light, the moon, acrylic on canvas 30cm_2016 / 300,000원"
        },
        {
          "imgSrc": "https://i0.wp.com/7pictures.co.kr/wp-content/uploads/2016/10/%ED%81%AC%EA%B8%B0%EB%B3%80%ED%99%98_KakaoTalk_20161012_114414382.jpg?zoom=2&fit=710%2C710&ssl=1",
          "description": "Blossom light, the moon, acrylic on canvas 30cm_2016 / 300,000원"
        }
      ]
    },
    {
      "title": "'Across the Universe' 어지인 작가",
      "creator": {
        "name": "어지인",
        "iconSrc": "https://7pictures.co.kr/wp-content/plugins/korea-sns/icons/facebook.png"
      },
      "imgSrc": "/assets/images/magazine-thumbnail.jpg",
      "category": "문화공간",
      "descriptions": [
        "관객과 작품으로 소통하기 위해서",
        "누구나 알고 있는 자연을 작품의 소재로 선택하고,",
        "나만의 색과 기법을 통해 작품에 감성을 담아낸다."
      ],
      "contents": [
        {
          "type": "text",
          "content": "관객과 작품으로 소통하기 위해서 누구나 알고 있는 자연을 작품의 소재로 선택하고, 나만의 색과 기법을 통해 작품에 감성을 담아낸다. 관객 또한 자연을 그린 작품을 보며 자신만의 감성으로 그 대상을 받아드린다.\n\n\t결국 작품은 하나이지만 그 작품이 다양한 의미로 다시 태어나는 것, 그래서 작가와 관객 모두 작품을 통해 자신만의 감성을 경험하고 공유하는 것, 그것이 바로 내가 생각하는 작품을 통한 ‘소통’이다.\n\n\t이전 전시 : ‘색, 괜찮아 잘하고 있어’_어지인, 김태경"
        }
      ],
      "artworks": [
        {
          "imgSrc": "https://i0.wp.com/7pictures.co.kr/wp-content/uploads/2016/10/%ED%81%AC%EA%B8%B0%EB%B3%80%ED%99%98_KakaoTalk_20161012_114414382.jpg?zoom=2&fit=710%2C710&ssl=1",
          "description": "Blossom light, the moon, acrylic on canvas 30cm_2016 / 300,000원"
        },
        {
          "imgSrc": "https://i0.wp.com/7pictures.co.kr/wp-content/uploads/2016/10/%ED%81%AC%EA%B8%B0%EB%B3%80%ED%99%98_KakaoTalk_20161012_114414382.jpg?zoom=2&fit=710%2C710&ssl=1",
          "description": "Blossom light, the moon, acrylic on canvas 30cm_2016 / 300,000원"
        },
        {
          "imgSrc": "https://i0.wp.com/7pictures.co.kr/wp-content/uploads/2016/10/%ED%81%AC%EA%B8%B0%EB%B3%80%ED%99%98_KakaoTalk_20161012_114414382.jpg?zoom=2&fit=710%2C710&ssl=1",
          "description": "Blossom light, the moon, acrylic on canvas 30cm_2016 / 300,000원"
        },
        {
          "imgSrc": "https://i0.wp.com/7pictures.co.kr/wp-content/uploads/2016/10/%ED%81%AC%EA%B8%B0%EB%B3%80%ED%99%98_KakaoTalk_20161012_114414382.jpg?zoom=2&fit=710%2C710&ssl=1",
          "description": "Blossom light, the moon, acrylic on canvas 30cm_2016 / 300,000원"
        }
      ]
    },
    {
      "title": "'Across the Universe' 어지인 작가",
      "creator": {
        "name": "어지인",
        "iconSrc": "https://7pictures.co.kr/wp-content/plugins/korea-sns/icons/facebook.png"
      },
      "imgSrc": "/assets/images/magazine-thumbnail.jpg",
      "category": "문화공간",
      "descriptions": [
        "관객과 작품으로 소통하기 위해서",
        "누구나 알고 있는 자연을 작품의 소재로 선택하고,",
        "나만의 색과 기법을 통해 작품에 감성을 담아낸다."
      ],
      "contents": [
        {
          "type": "text",
          "content": "관객과 작품으로 소통하기 위해서 누구나 알고 있는 자연을 작품의 소재로 선택하고, 나만의 색과 기법을 통해 작품에 감성을 담아낸다. 관객 또한 자연을 그린 작품을 보며 자신만의 감성으로 그 대상을 받아드린다.\n\n\t결국 작품은 하나이지만 그 작품이 다양한 의미로 다시 태어나는 것, 그래서 작가와 관객 모두 작품을 통해 자신만의 감성을 경험하고 공유하는 것, 그것이 바로 내가 생각하는 작품을 통한 ‘소통’이다.\n\n\t이전 전시 : ‘색, 괜찮아 잘하고 있어’_어지인, 김태경"
        }
      ],
      "artworks": [
        {
          "imgSrc": "https://i0.wp.com/7pictures.co.kr/wp-content/uploads/2016/10/%ED%81%AC%EA%B8%B0%EB%B3%80%ED%99%98_KakaoTalk_20161012_114414382.jpg?zoom=2&fit=710%2C710&ssl=1",
          "description": "Blossom light, the moon, acrylic on canvas 30cm_2016 / 300,000원"
        },
        {
          "imgSrc": "https://i0.wp.com/7pictures.co.kr/wp-content/uploads/2016/10/%ED%81%AC%EA%B8%B0%EB%B3%80%ED%99%98_KakaoTalk_20161012_114414382.jpg?zoom=2&fit=710%2C710&ssl=1",
          "description": "Blossom light, the moon, acrylic on canvas 30cm_2016 / 300,000원"
        },
        {
          "imgSrc": "https://i0.wp.com/7pictures.co.kr/wp-content/uploads/2016/10/%ED%81%AC%EA%B8%B0%EB%B3%80%ED%99%98_KakaoTalk_20161012_114414382.jpg?zoom=2&fit=710%2C710&ssl=1",
          "description": "Blossom light, the moon, acrylic on canvas 30cm_2016 / 300,000원"
        },
        {
          "imgSrc": "https://i0.wp.com/7pictures.co.kr/wp-content/uploads/2016/10/%ED%81%AC%EA%B8%B0%EB%B3%80%ED%99%98_KakaoTalk_20161012_114414382.jpg?zoom=2&fit=710%2C710&ssl=1",
          "description": "Blossom light, the moon, acrylic on canvas 30cm_2016 / 300,000원"
        }
      ]
    },
    {
      "title": "'Across the Universe' 어지인 작가",
      "creator": {
        "name": "어지인",
        "iconSrc": "https://7pictures.co.kr/wp-content/plugins/korea-sns/icons/facebook.png"
      },
      "imgSrc": "/assets/images/magazine-thumbnail.jpg",
      "category": "문화공간",
      "descriptions": [
        "관객과 작품으로 소통하기 위해서",
        "누구나 알고 있는 자연을 작품의 소재로 선택하고,",
        "나만의 색과 기법을 통해 작품에 감성을 담아낸다."
      ],
      "contents": [
        {
          "type": "text",
          "content": "관객과 작품으로 소통하기 위해서 누구나 알고 있는 자연을 작품의 소재로 선택하고, 나만의 색과 기법을 통해 작품에 감성을 담아낸다. 관객 또한 자연을 그린 작품을 보며 자신만의 감성으로 그 대상을 받아드린다.\n\n\t결국 작품은 하나이지만 그 작품이 다양한 의미로 다시 태어나는 것, 그래서 작가와 관객 모두 작품을 통해 자신만의 감성을 경험하고 공유하는 것, 그것이 바로 내가 생각하는 작품을 통한 ‘소통’이다.\n\n\t이전 전시 : ‘색, 괜찮아 잘하고 있어’_어지인, 김태경"
        }
      ],
      "artworks": [
        {
          "imgSrc": "https://i0.wp.com/7pictures.co.kr/wp-content/uploads/2016/10/%ED%81%AC%EA%B8%B0%EB%B3%80%ED%99%98_KakaoTalk_20161012_114414382.jpg?zoom=2&fit=710%2C710&ssl=1",
          "description": "Blossom light, the moon, acrylic on canvas 30cm_2016 / 300,000원"
        },
        {
          "imgSrc": "https://i0.wp.com/7pictures.co.kr/wp-content/uploads/2016/10/%ED%81%AC%EA%B8%B0%EB%B3%80%ED%99%98_KakaoTalk_20161012_114414382.jpg?zoom=2&fit=710%2C710&ssl=1",
          "description": "Blossom light, the moon, acrylic on canvas 30cm_2016 / 300,000원"
        },
        {
          "imgSrc": "https://i0.wp.com/7pictures.co.kr/wp-content/uploads/2016/10/%ED%81%AC%EA%B8%B0%EB%B3%80%ED%99%98_KakaoTalk_20161012_114414382.jpg?zoom=2&fit=710%2C710&ssl=1",
          "description": "Blossom light, the moon, acrylic on canvas 30cm_2016 / 300,000원"
        },
        {
          "imgSrc": "https://i0.wp.com/7pictures.co.kr/wp-content/uploads/2016/10/%ED%81%AC%EA%B8%B0%EB%B3%80%ED%99%98_KakaoTalk_20161012_114414382.jpg?zoom=2&fit=710%2C710&ssl=1",
          "description": "Blossom light, the moon, acrylic on canvas 30cm_2016 / 300,000원"
        }
      ]
    },
    {
      "title": "'Across the Universe' 어지인 작가",
      "creator": {
        "name": "어지인",
        "iconSrc": "https://7pictures.co.kr/wp-content/plugins/korea-sns/icons/facebook.png"
      },
      "imgSrc": "/assets/images/magazine-thumbnail.jpg",
      "category": "문화공간",
      "descriptions": [
        "관객과 작품으로 소통하기 위해서",
        "누구나 알고 있는 자연을 작품의 소재로 선택하고,",
        "나만의 색과 기법을 통해 작품에 감성을 담아낸다."
      ],
      "contents": [
        {
          "type": "text",
          "content": "관객과 작품으로 소통하기 위해서 누구나 알고 있는 자연을 작품의 소재로 선택하고, 나만의 색과 기법을 통해 작품에 감성을 담아낸다. 관객 또한 자연을 그린 작품을 보며 자신만의 감성으로 그 대상을 받아드린다.\n\n\t결국 작품은 하나이지만 그 작품이 다양한 의미로 다시 태어나는 것, 그래서 작가와 관객 모두 작품을 통해 자신만의 감성을 경험하고 공유하는 것, 그것이 바로 내가 생각하는 작품을 통한 ‘소통’이다.\n\n\t이전 전시 : ‘색, 괜찮아 잘하고 있어’_어지인, 김태경"
        }
      ],
      "artworks": [
        {
          "imgSrc": "https://i0.wp.com/7pictures.co.kr/wp-content/uploads/2016/10/%ED%81%AC%EA%B8%B0%EB%B3%80%ED%99%98_KakaoTalk_20161012_114414382.jpg?zoom=2&fit=710%2C710&ssl=1",
          "description": "Blossom light, the moon, acrylic on canvas 30cm_2016 / 300,000원"
        },
        {
          "imgSrc": "https://i0.wp.com/7pictures.co.kr/wp-content/uploads/2016/10/%ED%81%AC%EA%B8%B0%EB%B3%80%ED%99%98_KakaoTalk_20161012_114414382.jpg?zoom=2&fit=710%2C710&ssl=1",
          "description": "Blossom light, the moon, acrylic on canvas 30cm_2016 / 300,000원"
        },
        {
          "imgSrc": "https://i0.wp.com/7pictures.co.kr/wp-content/uploads/2016/10/%ED%81%AC%EA%B8%B0%EB%B3%80%ED%99%98_KakaoTalk_20161012_114414382.jpg?zoom=2&fit=710%2C710&ssl=1",
          "description": "Blossom light, the moon, acrylic on canvas 30cm_2016 / 300,000원"
        },
        {
          "imgSrc": "https://i0.wp.com/7pictures.co.kr/wp-content/uploads/2016/10/%ED%81%AC%EA%B8%B0%EB%B3%80%ED%99%98_KakaoTalk_20161012_114414382.jpg?zoom=2&fit=710%2C710&ssl=1",
          "description": "Blossom light, the moon, acrylic on canvas 30cm_2016 / 300,000원"
        }
      ]
    },
    {
      "title": "'Across the Universe' 어지인 작가",
      "creator": {
        "name": "어지인",
        "iconSrc": "https://7pictures.co.kr/wp-content/plugins/korea-sns/icons/facebook.png"
      },
      "imgSrc": "/assets/images/magazine-thumbnail.jpg",
      "category": "문화공간",
      "descriptions": [
        "관객과 작품으로 소통하기 위해서",
        "누구나 알고 있는 자연을 작품의 소재로 선택하고,",
        "나만의 색과 기법을 통해 작품에 감성을 담아낸다."
      ],
      "contents": [
        {
          "type": "text",
          "content": "관객과 작품으로 소통하기 위해서 누구나 알고 있는 자연을 작품의 소재로 선택하고, 나만의 색과 기법을 통해 작품에 감성을 담아낸다. 관객 또한 자연을 그린 작품을 보며 자신만의 감성으로 그 대상을 받아드린다.\n\n\t결국 작품은 하나이지만 그 작품이 다양한 의미로 다시 태어나는 것, 그래서 작가와 관객 모두 작품을 통해 자신만의 감성을 경험하고 공유하는 것, 그것이 바로 내가 생각하는 작품을 통한 ‘소통’이다.\n\n\t이전 전시 : ‘색, 괜찮아 잘하고 있어’_어지인, 김태경"
        }
      ],
      "artworks": [
        {
          "imgSrc": "https://i0.wp.com/7pictures.co.kr/wp-content/uploads/2016/10/%ED%81%AC%EA%B8%B0%EB%B3%80%ED%99%98_KakaoTalk_20161012_114414382.jpg?zoom=2&fit=710%2C710&ssl=1",
          "description": "Blossom light, the moon, acrylic on canvas 30cm_2016 / 300,000원"
        },
        {
          "imgSrc": "https://i0.wp.com/7pictures.co.kr/wp-content/uploads/2016/10/%ED%81%AC%EA%B8%B0%EB%B3%80%ED%99%98_KakaoTalk_20161012_114414382.jpg?zoom=2&fit=710%2C710&ssl=1",
          "description": "Blossom light, the moon, acrylic on canvas 30cm_2016 / 300,000원"
        },
        {
          "imgSrc": "https://i0.wp.com/7pictures.co.kr/wp-content/uploads/2016/10/%ED%81%AC%EA%B8%B0%EB%B3%80%ED%99%98_KakaoTalk_20161012_114414382.jpg?zoom=2&fit=710%2C710&ssl=1",
          "description": "Blossom light, the moon, acrylic on canvas 30cm_2016 / 300,000원"
        },
        {
          "imgSrc": "https://i0.wp.com/7pictures.co.kr/wp-content/uploads/2016/10/%ED%81%AC%EA%B8%B0%EB%B3%80%ED%99%98_KakaoTalk_20161012_114414382.jpg?zoom=2&fit=710%2C710&ssl=1",
          "description": "Blossom light, the moon, acrylic on canvas 30cm_2016 / 300,000원"
        }
      ]
    },
    {
      "title": "'Across the Universe' 어지인 작가",
      "creator": {
        "name": "어지인",
        "iconSrc": "https://7pictures.co.kr/wp-content/plugins/korea-sns/icons/facebook.png"
      },
      "imgSrc": "/assets/images/magazine-thumbnail.jpg",
      "category": "문화공간",
      "descriptions": [
        "관객과 작품으로 소통하기 위해서",
        "누구나 알고 있는 자연을 작품의 소재로 선택하고,",
        "나만의 색과 기법을 통해 작품에 감성을 담아낸다."
      ],
      "contents": [
        {
          "type": "text",
          "content": "관객과 작품으로 소통하기 위해서 누구나 알고 있는 자연을 작품의 소재로 선택하고, 나만의 색과 기법을 통해 작품에 감성을 담아낸다. 관객 또한 자연을 그린 작품을 보며 자신만의 감성으로 그 대상을 받아드린다.\n\n\t결국 작품은 하나이지만 그 작품이 다양한 의미로 다시 태어나는 것, 그래서 작가와 관객 모두 작품을 통해 자신만의 감성을 경험하고 공유하는 것, 그것이 바로 내가 생각하는 작품을 통한 ‘소통’이다.\n\n\t이전 전시 : ‘색, 괜찮아 잘하고 있어’_어지인, 김태경"
        }
      ],
      "artworks": [
        {
          "imgSrc": "https://i0.wp.com/7pictures.co.kr/wp-content/uploads/2016/10/%ED%81%AC%EA%B8%B0%EB%B3%80%ED%99%98_KakaoTalk_20161012_114414382.jpg?zoom=2&fit=710%2C710&ssl=1",
          "description": "Blossom light, the moon, acrylic on canvas 30cm_2016 / 300,000원"
        },
        {
          "imgSrc": "https://i0.wp.com/7pictures.co.kr/wp-content/uploads/2016/10/%ED%81%AC%EA%B8%B0%EB%B3%80%ED%99%98_KakaoTalk_20161012_114414382.jpg?zoom=2&fit=710%2C710&ssl=1",
          "description": "Blossom light, the moon, acrylic on canvas 30cm_2016 / 300,000원"
        },
        {
          "imgSrc": "https://i0.wp.com/7pictures.co.kr/wp-content/uploads/2016/10/%ED%81%AC%EA%B8%B0%EB%B3%80%ED%99%98_KakaoTalk_20161012_114414382.jpg?zoom=2&fit=710%2C710&ssl=1",
          "description": "Blossom light, the moon, acrylic on canvas 30cm_2016 / 300,000원"
        },
        {
          "imgSrc": "https://i0.wp.com/7pictures.co.kr/wp-content/uploads/2016/10/%ED%81%AC%EA%B8%B0%EB%B3%80%ED%99%98_KakaoTalk_20161012_114414382.jpg?zoom=2&fit=710%2C710&ssl=1",
          "description": "Blossom light, the moon, acrylic on canvas 30cm_2016 / 300,000원"
        }
      ]
    },
    {
      "title": "'Across the Universe' 어지인 작가",
      "creator": {
        "name": "어지인",
        "iconSrc": "https://7pictures.co.kr/wp-content/plugins/korea-sns/icons/facebook.png"
      },
      "imgSrc": "/assets/images/magazine-thumbnail.jpg",
      "category": "문화공간",
      "descriptions": [
        "관객과 작품으로 소통하기 위해서",
        "누구나 알고 있는 자연을 작품의 소재로 선택하고,",
        "나만의 색과 기법을 통해 작품에 감성을 담아낸다."
      ],
      "contents": [
        {
          "type": "text",
          "content": "관객과 작품으로 소통하기 위해서 누구나 알고 있는 자연을 작품의 소재로 선택하고, 나만의 색과 기법을 통해 작품에 감성을 담아낸다. 관객 또한 자연을 그린 작품을 보며 자신만의 감성으로 그 대상을 받아드린다.\n\n\t결국 작품은 하나이지만 그 작품이 다양한 의미로 다시 태어나는 것, 그래서 작가와 관객 모두 작품을 통해 자신만의 감성을 경험하고 공유하는 것, 그것이 바로 내가 생각하는 작품을 통한 ‘소통’이다.\n\n\t이전 전시 : ‘색, 괜찮아 잘하고 있어’_어지인, 김태경"
        }
      ],
      "artworks": [
        {
          "imgSrc": "https://i0.wp.com/7pictures.co.kr/wp-content/uploads/2016/10/%ED%81%AC%EA%B8%B0%EB%B3%80%ED%99%98_KakaoTalk_20161012_114414382.jpg?zoom=2&fit=710%2C710&ssl=1",
          "description": "Blossom light, the moon, acrylic on canvas 30cm_2016 / 300,000원"
        },
        {
          "imgSrc": "https://i0.wp.com/7pictures.co.kr/wp-content/uploads/2016/10/%ED%81%AC%EA%B8%B0%EB%B3%80%ED%99%98_KakaoTalk_20161012_114414382.jpg?zoom=2&fit=710%2C710&ssl=1",
          "description": "Blossom light, the moon, acrylic on canvas 30cm_2016 / 300,000원"
        },
        {
          "imgSrc": "https://i0.wp.com/7pictures.co.kr/wp-content/uploads/2016/10/%ED%81%AC%EA%B8%B0%EB%B3%80%ED%99%98_KakaoTalk_20161012_114414382.jpg?zoom=2&fit=710%2C710&ssl=1",
          "description": "Blossom light, the moon, acrylic on canvas 30cm_2016 / 300,000원"
        },
        {
          "imgSrc": "https://i0.wp.com/7pictures.co.kr/wp-content/uploads/2016/10/%ED%81%AC%EA%B8%B0%EB%B3%80%ED%99%98_KakaoTalk_20161012_114414382.jpg?zoom=2&fit=710%2C710&ssl=1",
          "description": "Blossom light, the moon, acrylic on canvas 30cm_2016 / 300,000원"
        }
      ]
    },
    {
      "title": "'Across the Universe' 어지인 작가",
      "creator": {
        "name": "어지인",
        "iconSrc": "https://7pictures.co.kr/wp-content/plugins/korea-sns/icons/facebook.png"
      },
      "imgSrc": "/assets/images/magazine-thumbnail.jpg",
      "category": "문화공간",
      "descriptions": [
        "관객과 작품으로 소통하기 위해서",
        "누구나 알고 있는 자연을 작품의 소재로 선택하고,",
        "나만의 색과 기법을 통해 작품에 감성을 담아낸다."
      ],
      "contents": [
        {
          "type": "text",
          "content": "관객과 작품으로 소통하기 위해서 누구나 알고 있는 자연을 작품의 소재로 선택하고, 나만의 색과 기법을 통해 작품에 감성을 담아낸다. 관객 또한 자연을 그린 작품을 보며 자신만의 감성으로 그 대상을 받아드린다.\n\n\t결국 작품은 하나이지만 그 작품이 다양한 의미로 다시 태어나는 것, 그래서 작가와 관객 모두 작품을 통해 자신만의 감성을 경험하고 공유하는 것, 그것이 바로 내가 생각하는 작품을 통한 ‘소통’이다.\n\n\t이전 전시 : ‘색, 괜찮아 잘하고 있어’_어지인, 김태경"
        }
      ],
      "artworks": [
        {
          "imgSrc": "https://i0.wp.com/7pictures.co.kr/wp-content/uploads/2016/10/%ED%81%AC%EA%B8%B0%EB%B3%80%ED%99%98_KakaoTalk_20161012_114414382.jpg?zoom=2&fit=710%2C710&ssl=1",
          "description": "Blossom light, the moon, acrylic on canvas 30cm_2016 / 300,000원"
        },
        {
          "imgSrc": "https://i0.wp.com/7pictures.co.kr/wp-content/uploads/2016/10/%ED%81%AC%EA%B8%B0%EB%B3%80%ED%99%98_KakaoTalk_20161012_114414382.jpg?zoom=2&fit=710%2C710&ssl=1",
          "description": "Blossom light, the moon, acrylic on canvas 30cm_2016 / 300,000원"
        },
        {
          "imgSrc": "https://i0.wp.com/7pictures.co.kr/wp-content/uploads/2016/10/%ED%81%AC%EA%B8%B0%EB%B3%80%ED%99%98_KakaoTalk_20161012_114414382.jpg?zoom=2&fit=710%2C710&ssl=1",
          "description": "Blossom light, the moon, acrylic on canvas 30cm_2016 / 300,000원"
        },
        {
          "imgSrc": "https://i0.wp.com/7pictures.co.kr/wp-content/uploads/2016/10/%ED%81%AC%EA%B8%B0%EB%B3%80%ED%99%98_KakaoTalk_20161012_114414382.jpg?zoom=2&fit=710%2C710&ssl=1",
          "description": "Blossom light, the moon, acrylic on canvas 30cm_2016 / 300,000원"
        }
      ]
    },
    {
      "title": "'Across the Universe' 어지인 작가",
      "creator": {
        "name": "어지인",
        "iconSrc": "https://7pictures.co.kr/wp-content/plugins/korea-sns/icons/facebook.png"
      },
      "imgSrc": "/assets/images/magazine-thumbnail.jpg",
      "category": "문화공간",
      "descriptions": [
        "관객과 작품으로 소통하기 위해서",
        "누구나 알고 있는 자연을 작품의 소재로 선택하고,",
        "나만의 색과 기법을 통해 작품에 감성을 담아낸다."
      ],
      "contents": [
        {
          "type": "text",
          "content": "관객과 작품으로 소통하기 위해서 누구나 알고 있는 자연을 작품의 소재로 선택하고, 나만의 색과 기법을 통해 작품에 감성을 담아낸다. 관객 또한 자연을 그린 작품을 보며 자신만의 감성으로 그 대상을 받아드린다.\n\n\t결국 작품은 하나이지만 그 작품이 다양한 의미로 다시 태어나는 것, 그래서 작가와 관객 모두 작품을 통해 자신만의 감성을 경험하고 공유하는 것, 그것이 바로 내가 생각하는 작품을 통한 ‘소통’이다.\n\n\t이전 전시 : ‘색, 괜찮아 잘하고 있어’_어지인, 김태경"
        }
      ],
      "artworks": [
        {
          "imgSrc": "https://i0.wp.com/7pictures.co.kr/wp-content/uploads/2016/10/%ED%81%AC%EA%B8%B0%EB%B3%80%ED%99%98_KakaoTalk_20161012_114414382.jpg?zoom=2&fit=710%2C710&ssl=1",
          "description": "Blossom light, the moon, acrylic on canvas 30cm_2016 / 300,000원"
        },
        {
          "imgSrc": "https://i0.wp.com/7pictures.co.kr/wp-content/uploads/2016/10/%ED%81%AC%EA%B8%B0%EB%B3%80%ED%99%98_KakaoTalk_20161012_114414382.jpg?zoom=2&fit=710%2C710&ssl=1",
          "description": "Blossom light, the moon, acrylic on canvas 30cm_2016 / 300,000원"
        },
        {
          "imgSrc": "https://i0.wp.com/7pictures.co.kr/wp-content/uploads/2016/10/%ED%81%AC%EA%B8%B0%EB%B3%80%ED%99%98_KakaoTalk_20161012_114414382.jpg?zoom=2&fit=710%2C710&ssl=1",
          "description": "Blossom light, the moon, acrylic on canvas 30cm_2016 / 300,000원"
        },
        {
          "imgSrc": "https://i0.wp.com/7pictures.co.kr/wp-content/uploads/2016/10/%ED%81%AC%EA%B8%B0%EB%B3%80%ED%99%98_KakaoTalk_20161012_114414382.jpg?zoom=2&fit=710%2C710&ssl=1",
          "description": "Blossom light, the moon, acrylic on canvas 30cm_2016 / 300,000원"
        }
      ]
    },
    {
      "title": "'Across the Universe' 어지인 작가",
      "creator": {
        "name": "어지인",
        "iconSrc": "https://7pictures.co.kr/wp-content/plugins/korea-sns/icons/facebook.png"
      },
      "imgSrc": "/assets/images/magazine-thumbnail.jpg",
      "category": "문화공간",
      "descriptions": [
        "관객과 작품으로 소통하기 위해서",
        "누구나 알고 있는 자연을 작품의 소재로 선택하고,",
        "나만의 색과 기법을 통해 작품에 감성을 담아낸다."
      ],
      "contents": [
        {
          "type": "text",
          "content": "관객과 작품으로 소통하기 위해서 누구나 알고 있는 자연을 작품의 소재로 선택하고, 나만의 색과 기법을 통해 작품에 감성을 담아낸다. 관객 또한 자연을 그린 작품을 보며 자신만의 감성으로 그 대상을 받아드린다.\n\n\t결국 작품은 하나이지만 그 작품이 다양한 의미로 다시 태어나는 것, 그래서 작가와 관객 모두 작품을 통해 자신만의 감성을 경험하고 공유하는 것, 그것이 바로 내가 생각하는 작품을 통한 ‘소통’이다.\n\n\t이전 전시 : ‘색, 괜찮아 잘하고 있어’_어지인, 김태경"
        }
      ],
      "artworks": [
        {
          "imgSrc": "https://i0.wp.com/7pictures.co.kr/wp-content/uploads/2016/10/%ED%81%AC%EA%B8%B0%EB%B3%80%ED%99%98_KakaoTalk_20161012_114414382.jpg?zoom=2&fit=710%2C710&ssl=1",
          "description": "Blossom light, the moon, acrylic on canvas 30cm_2016 / 300,000원"
        },
        {
          "imgSrc": "https://i0.wp.com/7pictures.co.kr/wp-content/uploads/2016/10/%ED%81%AC%EA%B8%B0%EB%B3%80%ED%99%98_KakaoTalk_20161012_114414382.jpg?zoom=2&fit=710%2C710&ssl=1",
          "description": "Blossom light, the moon, acrylic on canvas 30cm_2016 / 300,000원"
        },
        {
          "imgSrc": "https://i0.wp.com/7pictures.co.kr/wp-content/uploads/2016/10/%ED%81%AC%EA%B8%B0%EB%B3%80%ED%99%98_KakaoTalk_20161012_114414382.jpg?zoom=2&fit=710%2C710&ssl=1",
          "description": "Blossom light, the moon, acrylic on canvas 30cm_2016 / 300,000원"
        },
        {
          "imgSrc": "https://i0.wp.com/7pictures.co.kr/wp-content/uploads/2016/10/%ED%81%AC%EA%B8%B0%EB%B3%80%ED%99%98_KakaoTalk_20161012_114414382.jpg?zoom=2&fit=710%2C710&ssl=1",
          "description": "Blossom light, the moon, acrylic on canvas 30cm_2016 / 300,000원"
        }
      ]
    }
  ]
}
